mathcom/__init__.py
mathcom-0.1.dist-info/METADATA
mathcom-0.1.dist-info/WHEEL
mathcom-0.1.dist-info/licenses/LICENSE
mathcom-0.1.dist-info/RECORD
