Metadata-Version: 2.4
Name: mathcom
Version: 0.1
Summary: World Great Math - Mathcom
Project-URL: Homepage, https://github.com/LeThanhNhan2013/mathcom
Project-URL: Issues, https://github.com/LeThanhNhan2013/mathcom/issues
Author-email: LeThanhNhan2013 <lethanhnhan1172@gmail.com>
License-File: LICENSE
Classifier: License :: OSI Approved :: GNU General Public License v3 (GPLv3)
Classifier: Operating System :: OS Independent
Classifier: Programming Language :: Python :: 3
Requires-Python: >=2.5
